ymlconf/__init__.py
ymlconf/_version.py
ymlconf/attribute.py
ymlconf/common.py
ymlconf/yaml_config_manager.py
ymlconf-2.0.0.dist-info/AUTHORS.rst
ymlconf-2.0.0.dist-info/LICENSE
ymlconf-2.0.0.dist-info/METADATA
ymlconf-2.0.0.dist-info/WHEEL
ymlconf-2.0.0.dist-info/top_level.txt
ymlconf-2.0.0.dist-info/RECORD
